setup.py
bodatools/__init__.py
bodatools.egg-info/PKG-INFO
bodatools.egg-info/SOURCES.txt
bodatools.egg-info/dependency_links.txt
bodatools.egg-info/top_level.txt
bodatools/binfile/__init__.py
bodatools/binfile/core.py
bodatools/binfile/eudora.py
bodatools/binfile/outlookexpress.py
scripts/export-email
test/test_all.py
test/testcore.py