Metadata-Version: 1.0
Name: bodatools
Version: 0.1.0
Summary: A collection of python utilities and scripts for working with binary files
Home-page: https://github.com/emory-libraries/bodatools
Author: Emory University Libraries
Author-email: libsysdev-l@listserv.cc.emory.edu
License: Apache License, Version 2.0
Platform: UNKNOWN
Classifier: Development Status :: 4 - Beta
Classifier: Environment :: Console
Classifier: Intended Audience :: Developers
Classifier: Intended Audience :: End Users/Desktop
Classifier: License :: OSI Approved :: Apache Software License
Classifier: Natural Language :: English
Classifier: Operating System :: OS Independent
Classifier: Programming Language :: Python
Classifier: Topic :: Software Development :: Libraries :: Python Modules
Classifier: Topic :: Utilities
